AgenticWrapper/__init__.py
agenticwrapper-0.1.2.dist-info/METADATA
agenticwrapper-0.1.2.dist-info/WHEEL
agenticwrapper-0.1.2.dist-info/licenses/LICENSE
agenticwrapper-0.1.2.dist-info/RECORD
