Metadata-Version: 2.4
Name: AgenticWrapper
Version: 0.1.2
Summary: A lightweight Python framework for adding agent capabilities (tools calling, memory, structured outputs) to single custom LLM functions
Project-URL: Homepage, https://github.com/lxl66566/AgenticWrapper
Project-URL: Repository, https://github.com/lxl66566/AgenticWrapper.git
Project-URL: Bug Tracker, https://github.com/lxl66566/AgenticWrapper/issues
Author-email: lxl66566 <lxl66566@gmail.com>
License: MIT
License-File: LICENSE
Keywords: agent,ai,framework,llm,wrapper
Classifier: Intended Audience :: Developers
Classifier: License :: OSI Approved :: MIT License
Classifier: Programming Language :: Python :: 3
Classifier: Programming Language :: Python :: 3.10
Classifier: Programming Language :: Python :: 3.11
Classifier: Programming Language :: Python :: 3.12
Classifier: Topic :: Scientific/Engineering :: Artificial Intelligence
Classifier: Topic :: Software Development :: Libraries :: Python Modules
Requires-Python: >=3.10
